{
    "startup_message": "Bonjour, je suis \u00e0 votre \u00e9coute.",
    "app_error": "Erreur lors du lancement de l'application.",
    "time_response": "Il est actuellement {time}.",
    "calc_error": "Je n'ai pas compris le calcul.",
    "search_done": "Voici les r\u00e9sultats pour {query}.",
    "search_error": "Erreur lors de la recherche.",
    "gemini_mode": "Je suis pr\u00eat \u00e0 discuter.",
    "gemini_idle": "Je suis pr\u00eat \u00e0 discuter en mode Gemini.",
    "gemini_error": "Erreur lors de la communication avec Gemini.",
    "gemini_image_error": "Erreur lors du traitement de l'image avec Gemini",
    "screenshot_question": "Que souhaitez-vous faire avec la capture d'\u00e9cran ?",
    "webcam_question": "Que souhaitez-vous faire avec l'image de la webcam ?",
    "screenshot_import_error": "Erreur: La biblioth\u00e8que PyAutoGUI n'est pas install\u00e9e. Veuillez l'installer.",
    "webcam_error": "Impossible de lire la webcam",
    "webcam_capture_error": "Une erreur s'est produite lors de la capture de l'image avec la webcam.",
    "image_process_error": "Erreur: Le format de l'image n'est pas support\u00e9",
    "image_saved": "Image sauvegard\u00e9e en tant que {filepath}",
    "image_save_error": "Erreur lors de la sauvegarde de l'image",
    "command_notfound": "Commande non reconnue.",
    "wiki_notfound": "Page introuvable sur Wikipedia",
    "mode_standard": "Je repasse en mode standard.",
    "file_error": "Erreur lors de l'ouverture du fichier",
    "note_prompt": "Que souhaitez-vous noter?",
    "note_saved": "Note enregistr\u00e9e dans {filepath}",
    "note_error": "Erreur lors de la sauvegarde de la note",
    "calculate_prompt": "Quel calcul souhaitez-vous effectuer ?",
    "speech_to_text_start": "Saisie vocale activ\u00e9e",
    "speech_to_text_stop": "Saisie vocale d\u00e9sactiv\u00e9e",
    "schedule_command_prompt": "Quelle commande souhaitez-vous planifier ?",
    "schedule_success": "T\u00e2che planifi\u00e9e",
    "schedule_time_error": "Format de l'heure incorrect, veuillez r\u00e9essayer (HH:MM).",
    "schedule_error": "Erreur lors de la planification de la t\u00e2che",
    "schedule_no_command": "Je n'ai pas compris la commande.",
    "schedule_no_time": "Je n'ai pas compris l'heure.",
    "command_error": "Erreur lors de l'ex\u00e9cution de la commande",
    "schedule_time_prompt": "\u00c0 quelle heure souhaitez-vous l'ex\u00e9cuter ?",
    "file_opened": "Fichier ouvert !",
    "app_launched": "OK.",
    "folder_name_prompt": "Quel nom souhaitez-vous donner au dossier ?",
    "folder_created": "Dossier '{folder_name}' créé sur le bureau.",
    "folder_error": "Erreur lors de la création du dossier.",
    "folder_name_error": "Nom de dossier non spécifié."
}
